vedicpy/__init__.py
vedicpy/compliment.py
vedicpy/cube.py
vedicpy/cuberoot.py
vedicpy/divisibility.py
vedicpy/division.py
vedicpy/multiply.py
vedicpy/recurring.py
vedicpy/square.py
vedicpy/squareroot.py
vedicpy-0.1.0.dist-info/AUTHORS.rst
vedicpy-0.1.0.dist-info/LICENSE
vedicpy-0.1.0.dist-info/METADATA
vedicpy-0.1.0.dist-info/WHEEL
vedicpy-0.1.0.dist-info/top_level.txt
vedicpy-0.1.0.dist-info/RECORD
