Metadata-Version: 2.1
Name: vedicpy
Version: 0.1.0
Summary: A Python Package for Vedic Mathematics
Home-page: https://github.com/utkarsh0702/vedicpy
Author: Utkarsh Mishra
Author-email: utkarsh.um07@gmail.com
License: BSD
Platform: UNKNOWN
Classifier: Programming Language :: Python :: 3
Classifier: Programming Language :: Python :: 3.6
Classifier: Programming Language :: Python :: 3.7
Classifier: Programming Language :: Python :: 3.8
Classifier: License :: OSI Approved :: BSD License
Classifier: Operating System :: OS Independent
Requires-Python: >=3.6
